LICENSE
README.rst
ez_setup.py
setup.py
src/build/__init__.py
src/build/middleware.py
src/build/urls.py
src/build/management/__init__.py
src/build/management/commands/__init__.py
src/build/management/commands/build2s3.py
src/build/management/commands/s3setup.py
src/django_build.egg-info/PKG-INFO
src/django_build.egg-info/SOURCES.txt
src/django_build.egg-info/dependency_links.txt
src/django_build.egg-info/not-zip-safe
src/django_build.egg-info/requires.txt
src/django_build.egg-info/top_level.txt