Metadata-Version: 1.0
Name: django-build
Version: 0.2
Summary: django-build provides a management command 'build2s3' which tar and gzips the source code and stores it in s3.
Home-page: http://oppian.com/labs/django-build/
Author: Oppian
Author-email: matt@oppian.com
License: MIT
Keywords: django s3 build
Platform: UNKNOWN
Classifier: Development Status :: 3 - Alpha
Classifier: Environment :: Web Environment
Classifier: Intended Audience :: Developers
Classifier: License :: OSI Approved :: BSD License
Classifier: Operating System :: OS Independent
Classifier: Programming Language :: Python
Classifier: Framework :: Django
